underpants/__init__.py
underpants/engine.py
underpants/py.typed
underpants-0.2.4.dist-info/METADATA
underpants-0.2.4.dist-info/WHEEL
underpants-0.2.4.dist-info/namespace_packages.txt
underpants-0.2.4.dist-info/top_level.txt
underpants-0.2.4.dist-info/RECORD
