Metadata-Version: 2.1
Name: underpants
Version: 0.2.4
Summary: Leverage the Rules Engine from the Pants Build System as a library.
License: MIT
Project-URL: Documentation, https://github.com/kaos/underpants/wiki
Project-URL: Source, https://github.com/kaos/underpants
Project-URL: Tracker, https://github.com/kaos/underpants/issues
Classifier: Development Status :: 2 - Pre-Alpha
Classifier: Intended Audience :: Developers
Classifier: License :: OSI Approved :: MIT License
Classifier: Operating System :: MacOS :: MacOS X
Classifier: Operating System :: POSIX :: Linux
Classifier: Programming Language :: Python :: 3.9
Classifier: Programming Language :: Python
Classifier: Topic :: Software Development :: Libraries
Requires-Python: <3.10,>=3.9
Requires-Dist: pantsbuild.pants (<2.15,>=2.14.0a0)
